{
  "project_info": {
    "project_number": "335129986215",
    "firebase_url": "https://cidadeativa-6d007.firebaseio.com",
    "project_id": "cidadeativa-6d007",
    "storage_bucket": "cidadeativa-6d007.appspot.com"
  },
  "client": [
    {
      "client_info": {
        "mobilesdk_app_id": "1:335129986215:android:36c7d50a5cce6848",
        "android_client_info": {
          "package_name": "com.gravatai.cidadeativa"
        }
      },
      "oauth_client": [
        {
          "client_id": "335129986215-egnvhqco1u09fdfmea713bohk5aoho2s.apps.googleusercontent.com",
          "client_type": 1,
          "android_info": {
            "package_name": "com.gravatai.cidadeativa",
            "certificate_hash": "162110c493577ee27671d3d90703d759fe0c2d24"
          }
        },
        {
          "client_id": "335129986215-5i11luafdlol9g35ftd8u7293t5nusmr.apps.googleusercontent.com",
          "client_type": 3
        }
      ],
      "api_key": [
        {
          "current_key": "AIzaSyAAHtbKcPv9Jh5CcfGBRahEVzb2CNMNM-M"
        }
      ],
      "services": {
        "analytics_service": {
          "status": 1
        },
        "appinvite_service": {
          "status": 2,
          "other_platform_oauth_client": [
            {
              "client_id": "335129986215-5i11luafdlol9g35ftd8u7293t5nusmr.apps.googleusercontent.com",
              "client_type": 3
            }
          ]
        },
        "ads_service": {
          "status": 2
        }
      }
    }
  ],
  "configuration_version": "1"
}